another_ayx_plugin_cli/__init__.py
another_ayx_plugin_cli/__main__.py
another_ayx_plugin_cli/exceptions.py
another_ayx_plugin_cli/node_js_helpers.py
another_ayx_plugin_cli/validation.py
another_ayx_plugin_cli/version.py
another_ayx_plugin_cli/assets/__init__.py
another_ayx_plugin_cli/assets/templates/python/README_tests.md
another_ayx_plugin_cli/assets/templates/python/__init__.j2
another_ayx_plugin_cli/assets/templates/python/clean_plugin_tests.j2
another_ayx_plugin_cli/assets/templates/python/plugin.j2
another_ayx_plugin_cli/assets/templates/python/plugin_tests.j2
another_ayx_plugin_cli/assets/templates/python/requirements-local.j2
another_ayx_plugin_cli/assets/templates/python/requirements-thirdparty.j2
another_ayx_plugin_cli/assets/templates/python/setup.j2
another_ayx_plugin_cli/assets/templates/python/workspace_bootstrap.j2
another_ayx_plugin_cli/assets/templates/python/macros/input.j2
another_ayx_plugin_cli/assets/templates/python/macros/multi_conn.j2
another_ayx_plugin_cli/assets/templates/python/macros/multi_input.j2
another_ayx_plugin_cli/assets/templates/python/macros/multi_output.j2
another_ayx_plugin_cli/assets/templates/python/macros/optional.j2
another_ayx_plugin_cli/assets/templates/python/macros/output.j2
another_ayx_plugin_cli/assets/templates/python/macros/passthrough.j2
another_ayx_plugin_cli/assets/workspace_files/.gitignore
another_ayx_plugin_cli/assets/workspace_files/README.md
another_ayx_plugin_cli/assets/workspace_files/default_package_icon.png
another_ayx_plugin_cli/assets/workspace_files/ui_artifact.zip
another_ayx_plugin_cli/assets/workspace_files/yxi_bootstrap.py
another_ayx_plugin_cli/assets/workspace_files/ui_template/README.md
another_ayx_plugin_cli/ayx_workspace/__init__.py
another_ayx_plugin_cli/ayx_workspace/constants.py
another_ayx_plugin_cli/ayx_workspace/template_engine.py
another_ayx_plugin_cli/ayx_workspace/template_tool_settings.py
another_ayx_plugin_cli/ayx_workspace/__pycache__/__init__.cpython-310.pyc
another_ayx_plugin_cli-2.0.2.dist-info/licenses/LICENSE
another_ayx_plugin_cli-2.0.2.dist-info/METADATA
another_ayx_plugin_cli-2.0.2.dist-info/WHEEL
another_ayx_plugin_cli-2.0.2.dist-info/entry_points.txt
another_ayx_plugin_cli-2.0.2.dist-info/top_level.txt
another_ayx_plugin_cli-2.0.2.dist-info/RECORD
