Metadata-Version: 2.4
Name: another-ayx-plugin-cli
Version: 2.0.2
Summary: Command Line Interface for Alteryx Plugin Development
Author-email: Jupiter Bakakeu <jupiter.bakakeu@gmail.com>
Maintainer-email: Jupiter Bakakeu <jupiter.bakakeu@gmail.com>
License-Expression: MIT
Project-URL: Homepage, https://github.com/jupiterbak/another-ayx-plugin-cli
Project-URL: Repository, https://github.com/jupiterbak/another-ayx-plugin-cli.git
Classifier: Development Status :: 5 - Production/Stable
Classifier: Intended Audience :: Developers
Classifier: Programming Language :: Python :: 3
Classifier: Programming Language :: Python :: 3.8
Classifier: Programming Language :: Python :: 3.9
Classifier: Programming Language :: Python :: 3.10
Classifier: Topic :: Software Development :: Libraries :: Python Modules
Classifier: Topic :: Software Development :: Build Tools
Classifier: Environment :: Console
Requires-Python: >=3.8
License-File: LICENSE
Requires-Dist: typer
Requires-Dist: pydantic
Requires-Dist: packaging
Requires-Dist: jinja2
Requires-Dist: requests
Requires-Dist: doit>=0.36.0
Requires-Dist: xmltodict
Requires-Dist: pyyaml
Requires-Dist: click
Requires-Dist: typing-extensions
Requires-Dist: twine
Requires-Dist: pyarrow
Provides-Extra: dev
Requires-Dist: pytest; extra == "dev"
Requires-Dist: black; extra == "dev"
Requires-Dist: isort; extra == "dev"
Requires-Dist: flake8; extra == "dev"
Requires-Dist: mypy; extra == "dev"
Dynamic: license-file
